[
  {
    "id": "c5699909-9045-4d52-9a8d-f1102c17624c",
    "description": "Oil Change",
    "price": 45
  },
  {
    "id": "4862992d-f836-436e-a3be-552e004f5ade",
    "description": "Brake Pad Replacement (Front)",
    "price": 120
  },
  {
    "id": "3a23db72-7e17-4bd6-80a8-e27f1ebeeb9f",
    "description": "Brake Pad Replacement (Rear)",
    "price": 110
  },
  {
    "id": "2d639c2b-02a2-4a32-becd-aa161bf6e62b",
    "description": "Brake Rotor Replacement (Front)",
    "price": 150
  },
  {
    "id": "04802f02-8b40-43cb-bccf-5db747d961c2",
    "description": "Brake Rotor Replacement (Rear)",
    "price": 140
  },
  {
    "id": "1c541dc7-8ecd-4e3f-b200-482a6252d576",
    "description": "Spark Plug Replacement",
    "price": 90
  },
  {
    "id": "f8e48bbd-67c2-4548-bfb6-01e64b818ac6",
    "description": "Battery Replacement",
    "price": 50
  },
  {
    "id": "7ed5de42-f1ce-4efa-a5ba-6cfa64addc3e",
    "description": "Alternator Replacement",
    "price": 180
  },
  {
    "id": "06494e79-a752-4b27-9843-abbd827a4979",
    "description": "Starter Motor Replacement",
    "price": 160
  },
  {
    "id": "a6f4a5d4-db3b-4e24-bac1-c90e5ac291a5",
    "description": "Radiator Replacement",
    "price": 200
  },
  {
    "id": "49400891-7c07-49e9-a4db-19627276aa13",
    "description": "Water Pump Replacement",
    "price": 170
  },
  {
    "id": "9bc9b37a-0fb4-4e01-8bbe-139f8096029b",
    "description": "Timing Belt Replacement",
    "price": 350
  },
  {
    "id": "440c79f9-6e0a-48dd-8724-2a65f6e97c32",
    "description": "Fuel Pump Replacement",
    "price": 250
  },
  {
    "id": "c3a55c87-0b3e-42dd-aec6-9fc824072056",
    "description": "Oxygen Sensor Replacement",
    "price": 100
  },
  {
    "id": "890d3e91-9690-427f-a351-374ced4652fa",
    "description": "Diagnostic Service",
    "price": 75
  }
]